cinereader/__init__.py
cinereader/cinereader.py
cinereader-1.4.3.dist-info/LICENSE
cinereader-1.4.3.dist-info/METADATA
cinereader-1.4.3.dist-info/WHEEL
cinereader-1.4.3.dist-info/top_level.txt
cinereader-1.4.3.dist-info/RECORD
