Metadata-Version: 2.2
Name: cinereader
Version: 1.4.3
Summary: Python based Cine Decoder to get a Phantom cine file metadata and pixel arrays
Author-email: Vision Research <phantom-support@ametek.com>
License: GPL-3.0-or-later
Classifier: Programming Language :: Python :: 3
Classifier: Operating System :: OS Independent
Requires-Python: >=3.10
License-File: LICENSE
Requires-Dist: numpy>=2.2
Requires-Dist: pandas
Requires-Dist: numba
